keras_hist_graph/__init__.py
keras_hist_graph/keras_hist_graph.py
keras_hist_graph-0.0.3.dist-info/LICENSE
keras_hist_graph-0.0.3.dist-info/METADATA
keras_hist_graph-0.0.3.dist-info/WHEEL
keras_hist_graph-0.0.3.dist-info/top_level.txt
keras_hist_graph-0.0.3.dist-info/RECORD
