Metadata-Version: 2.1
Name: keras-hist-graph
Version: 0.0.3
Summary: Graph Keras training history object
Home-page: https://github.com/whyboris/keras-hist-graph
Author: Boris Yakubchik
Author-email: yboris@yahoo.com
License: MIT
Keywords: keras,jupyter
Platform: UNKNOWN
Classifier: Programming Language :: Python :: 3
Classifier: License :: OSI Approved :: MIT License
Classifier: Operating System :: OS Independent
Requires-Dist: Keras
Requires-Dist: matplotlib
